{
  "month_key": "2026-06",
  "month_label": "June 2026",
  "grand": {
    "leads_created": 4044,
    "booked": 642,
    "showed": 374,
    "qualified": 338,
    "closed": 64,
    "revenue": 481064.0
  },
  "groups": {
    "IN-HOUSE": {
      "leads_created": 3682,
      "booked": 495,
      "showed": 269,
      "qualified": 245,
      "closed": 47,
      "revenue": 366112.0
    },
    "EXTERNAL": {
      "leads_created": 147,
      "booked": 140,
      "showed": 104,
      "qualified": 92,
      "closed": 16,
      "revenue": 108955.0
    },
    "UNCATEGORIZED": {
      "leads_created": 214,
      "booked": 6,
      "showed": 0,
      "qualified": 0,
      "closed": 0,
      "revenue": 0.0
    }
  },
  "funnels": {
    "Reactivation Scrapers": {
      "leads_created": 112,
      "booked": 211,
      "book_pct": 188.4,
      "showed": 90,
      "show_pct": 42.7,
      "qualified": 75,
      "qual_pct": 35.5,
      "closed": 10,
      "cw_pct": 4.7,
      "revenue": 80973.0
    },
    "Instagram": {
      "leads_created": 119,
      "booked": 111,
      "book_pct": 93.3,
      "showed": 80,
      "show_pct": 72.1,
      "qualified": 70,
      "qual_pct": 63.1,
      "closed": 13,
      "cw_pct": 11.7,
      "revenue": 81464.0
    },
    "Unknown (Needs Review)": {
      "leads_created": 214,
      "booked": 6,
      "book_pct": 2.8,
      "showed": 0,
      "show_pct": 0.0,
      "qualified": 0,
      "qual_pct": 0.0,
      "closed": 0,
      "cw_pct": 0.0,
      "revenue": 0.0
    },
    "Internal Webinar": {
      "leads_created": 1426,
      "booked": 85,
      "book_pct": 6.0,
      "showed": 45,
      "show_pct": 52.9,
      "qualified": 43,
      "qual_pct": 50.6,
      "closed": 3,
      "cw_pct": 3.5,
      "revenue": 37991.0
    },
    "Meta Ads": {
      "leads_created": 208,
      "booked": 22,
      "book_pct": 10.6,
      "showed": 15,
      "show_pct": 68.2,
      "qualified": 13,
      "qual_pct": 59.1,
      "closed": 0,
      "cw_pct": 0.0,
      "revenue": 0.0
    },
    "Website": {
      "leads_created": 100,
      "booked": 104,
      "book_pct": 104.0,
      "showed": 60,
      "show_pct": 57.7,
      "qualified": 59,
      "qual_pct": 56.7,
      "closed": 14,
      "cw_pct": 13.5,
      "revenue": 98958.0
    },
    "X": {
      "leads_created": 6,
      "booked": 3,
      "book_pct": 50.0,
      "showed": 3,
      "show_pct": 100.0,
      "qualified": 3,
      "qual_pct": 100.0,
      "closed": 1,
      "cw_pct": 33.3,
      "revenue": 12497.0
    },
    "YouTube": {
      "leads_created": 81,
      "booked": 61,
      "book_pct": 75.3,
      "showed": 49,
      "show_pct": 80.3,
      "qualified": 45,
      "qual_pct": 73.8,
      "closed": 13,
      "cw_pct": 21.3,
      "revenue": 94211.0
    },
    "Anthony X": {
      "leads_created": 1,
      "booked": 1,
      "book_pct": 100.0,
      "showed": 1,
      "show_pct": 100.0,
      "qualified": 1,
      "qual_pct": 100.0,
      "closed": 1,
      "cw_pct": 100.0,
      "revenue": 5997.0
    },
    "LTF - In-House": {
      "leads_created": 993,
      "booked": 8,
      "book_pct": 0.8,
      "showed": 6,
      "show_pct": 75.0,
      "qualified": 6,
      "qual_pct": 75.0,
      "closed": 3,
      "cw_pct": 37.5,
      "revenue": 23991.0
    },
    "Low Ticket Funnel": {
      "leads_created": 13,
      "booked": 18,
      "book_pct": 138.5,
      "showed": 13,
      "show_pct": 72.2,
      "qualified": 11,
      "qual_pct": 61.1,
      "closed": 1,
      "cw_pct": 5.6,
      "revenue": 5997.0
    },
    "Linkedin": {
      "leads_created": 9,
      "booked": 8,
      "book_pct": 88.9,
      "showed": 8,
      "show_pct": 100.0,
      "qualified": 8,
      "qual_pct": 100.0,
      "closed": 1,
      "cw_pct": 12.5,
      "revenue": 8997.0
    },
    "Sales Reactivation": {
      "leads_created": 0,
      "booked": 1,
      "book_pct": 0,
      "showed": 1,
      "show_pct": 100.0,
      "qualified": 1,
      "qual_pct": 100.0,
      "closed": 1,
      "cw_pct": 100.0,
      "revenue": 5997.0
    },
    "Google Ads": {
      "leads_created": 2,
      "booked": 2,
      "book_pct": 100.0,
      "showed": 2,
      "show_pct": 100.0,
      "qualified": 2,
      "qual_pct": 100.0,
      "closed": 2,
      "cw_pct": 100.0,
      "revenue": 14994.0
    },
    "Reactivation Email": {
      "leads_created": 3,
      "booked": 1,
      "book_pct": 33.3,
      "showed": 1,
      "show_pct": 100.0,
      "qualified": 1,
      "qual_pct": 100.0,
      "closed": 1,
      "cw_pct": 100.0,
      "revenue": 8997.0
    },
    "VSL": {
      "leads_created": 7,
      "booked": 0,
      "book_pct": 0.0,
      "showed": 0,
      "show_pct": 0,
      "qualified": 0,
      "qual_pct": 0,
      "closed": 0,
      "cw_pct": 0,
      "revenue": 0.0
    },
    "WWWS": {
      "leads_created": 750,
      "booked": 0,
      "book_pct": 0.0,
      "showed": 0,
      "show_pct": 0,
      "qualified": 0,
      "qual_pct": 0,
      "closed": 0,
      "cw_pct": 0,
      "revenue": 0.0
    }
  }
}