{
  "month_key": "2026-06",
  "month_label": "June 2026",
  "grand": {
    "leads_created": 4032,
    "booked": 615,
    "showed": 371,
    "qualified": 333,
    "closed": 64,
    "revenue": 481064.0
  },
  "groups": {
    "IN-HOUSE": {
      "leads_created": 3674,
      "booked": 473,
      "showed": 266,
      "qualified": 241,
      "closed": 47,
      "revenue": 366112.0
    },
    "EXTERNAL": {
      "leads_created": 146,
      "booked": 138,
      "showed": 104,
      "qualified": 91,
      "closed": 16,
      "revenue": 108955.0
    },
    "UNCATEGORIZED": {
      "leads_created": 211,
      "booked": 3,
      "showed": 0,
      "qualified": 0,
      "closed": 0,
      "revenue": 0.0
    }
  },
  "funnels": {
    "Reactivation Scrapers": {
      "leads_created": 112,
      "booked": 197,
      "book_pct": 175.9,
      "showed": 88,
      "show_pct": 44.7,
      "qualified": 73,
      "qual_pct": 37.1,
      "closed": 10,
      "cw_pct": 5.1,
      "revenue": 80973.0
    },
    "Website": {
      "leads_created": 101,
      "booked": 97,
      "book_pct": 96.0,
      "showed": 59,
      "show_pct": 60.8,
      "qualified": 57,
      "qual_pct": 58.8,
      "closed": 14,
      "cw_pct": 14.4,
      "revenue": 98958.0
    },
    "Internal Webinar": {
      "leads_created": 1426,
      "booked": 86,
      "book_pct": 6.0,
      "showed": 45,
      "show_pct": 52.3,
      "qualified": 43,
      "qual_pct": 50.0,
      "closed": 3,
      "cw_pct": 3.5,
      "revenue": 37991.0
    },
    "Meta Ads": {
      "leads_created": 200,
      "booked": 20,
      "book_pct": 10.0,
      "showed": 15,
      "show_pct": 75.0,
      "qualified": 13,
      "qual_pct": 65.0,
      "closed": 0,
      "cw_pct": 0.0,
      "revenue": 0.0
    },
    "YouTube": {
      "leads_created": 81,
      "booked": 61,
      "book_pct": 75.3,
      "showed": 49,
      "show_pct": 80.3,
      "qualified": 45,
      "qual_pct": 73.8,
      "closed": 13,
      "cw_pct": 21.3,
      "revenue": 94211.0
    },
    "Instagram": {
      "leads_created": 117,
      "booked": 109,
      "book_pct": 93.2,
      "showed": 79,
      "show_pct": 72.5,
      "qualified": 68,
      "qual_pct": 62.4,
      "closed": 13,
      "cw_pct": 11.9,
      "revenue": 81464.0
    },
    "X": {
      "leads_created": 6,
      "booked": 3,
      "book_pct": 50.0,
      "showed": 3,
      "show_pct": 100.0,
      "qualified": 3,
      "qual_pct": 100.0,
      "closed": 1,
      "cw_pct": 33.3,
      "revenue": 12497.0
    },
    "LTF - In-House": {
      "leads_created": 993,
      "booked": 8,
      "book_pct": 0.8,
      "showed": 6,
      "show_pct": 75.0,
      "qualified": 6,
      "qual_pct": 75.0,
      "closed": 3,
      "cw_pct": 37.5,
      "revenue": 23991.0
    },
    "Low Ticket Funnel": {
      "leads_created": 13,
      "booked": 17,
      "book_pct": 130.8,
      "showed": 13,
      "show_pct": 76.5,
      "qualified": 11,
      "qual_pct": 64.7,
      "closed": 1,
      "cw_pct": 5.9,
      "revenue": 5997.0
    },
    "Linkedin": {
      "leads_created": 10,
      "booked": 9,
      "book_pct": 90.0,
      "showed": 9,
      "show_pct": 100.0,
      "qualified": 9,
      "qual_pct": 100.0,
      "closed": 1,
      "cw_pct": 11.1,
      "revenue": 8997.0
    },
    "Anthony X": {
      "leads_created": 1,
      "booked": 1,
      "book_pct": 100.0,
      "showed": 1,
      "show_pct": 100.0,
      "qualified": 1,
      "qual_pct": 100.0,
      "closed": 1,
      "cw_pct": 100.0,
      "revenue": 5997.0
    },
    "Sales Reactivation": {
      "leads_created": 0,
      "booked": 1,
      "book_pct": 0,
      "showed": 1,
      "show_pct": 100.0,
      "qualified": 1,
      "qual_pct": 100.0,
      "closed": 1,
      "cw_pct": 100.0,
      "revenue": 5997.0
    },
    "Google Ads": {
      "leads_created": 2,
      "booked": 2,
      "book_pct": 100.0,
      "showed": 2,
      "show_pct": 100.0,
      "qualified": 2,
      "qual_pct": 100.0,
      "closed": 2,
      "cw_pct": 100.0,
      "revenue": 14994.0
    },
    "Unknown (Needs Review)": {
      "leads_created": 211,
      "booked": 3,
      "book_pct": 1.4,
      "showed": 0,
      "show_pct": 0.0,
      "qualified": 0,
      "qual_pct": 0.0,
      "closed": 0,
      "cw_pct": 0.0,
      "revenue": 0.0
    },
    "Reactivation Email": {
      "leads_created": 3,
      "booked": 1,
      "book_pct": 33.3,
      "showed": 1,
      "show_pct": 100.0,
      "qualified": 1,
      "qual_pct": 100.0,
      "closed": 1,
      "cw_pct": 100.0,
      "revenue": 8997.0
    },
    "VSL": {
      "leads_created": 6,
      "booked": 0,
      "book_pct": 0.0,
      "showed": 0,
      "show_pct": 0,
      "qualified": 0,
      "qual_pct": 0,
      "closed": 0,
      "cw_pct": 0,
      "revenue": 0.0
    },
    "WWWS": {
      "leads_created": 750,
      "booked": 0,
      "book_pct": 0.0,
      "showed": 0,
      "show_pct": 0,
      "qualified": 0,
      "qual_pct": 0,
      "closed": 0,
      "cw_pct": 0,
      "revenue": 0.0
    }
  }
}